django_bullion/__init__.py
django_bullion/django_bullion.py
django_bullion-0.1.0.dist-info/AUTHORS.rst
django_bullion-0.1.0.dist-info/LICENSE
django_bullion-0.1.0.dist-info/METADATA
django_bullion-0.1.0.dist-info/WHEEL
django_bullion-0.1.0.dist-info/top_level.txt
django_bullion-0.1.0.dist-info/RECORD
