Metadata-Version: 2.1
Name: django-bullion
Version: 0.1.0
Summary: An agnostic package for working with Billing, Invoicing, and Payment Processing APIs
Home-page: https://github.com/watervize/django_bullion
Author: Jack Linke
Author-email: jack@watervize.com
License: MIT license
Keywords: django_bullion
Platform: UNKNOWN
Classifier: Development Status :: 2 - Pre-Alpha
Classifier: Intended Audience :: Developers
Classifier: License :: OSI Approved :: MIT License
Classifier: Natural Language :: English
Classifier: Programming Language :: Python :: 3
Classifier: Programming Language :: Python :: 3.5
Classifier: Programming Language :: Python :: 3.6
Classifier: Programming Language :: Python :: 3.7
Classifier: Programming Language :: Python :: 3.8
Requires-Python: >=3.5
